afip/__init__.py
afip/__main__.py
afip/credentials.py
afip/utils.py
afip/version.py
afip/ws.py
afip/ws_sr_padron_a13.py
afip/ws_sr_padron_a5.py
afip/wsaa.py
afip/wsfe.py
afip/wsfex.py
afip/zeep.py
afip-0.0.2.dist-info/LICENSE.txt
afip-0.0.2.dist-info/METADATA
afip-0.0.2.dist-info/WHEEL
afip-0.0.2.dist-info/top_level.txt
afip-0.0.2.dist-info/RECORD
