Metadata-Version: 2.1
Name: afip
Version: 0.0.2
Summary: Python package to interact with some of Argentina's AFIP Web services.
Home-page: https://github.com/mvillalba/python-afip
Author: Martín Raúl Villalba
Author-email: martin@martinvillalba.com
License: MIT
Platform: UNKNOWN
Classifier: Development Status :: 2 - Pre-Alpha
Classifier: Environment :: Console
Classifier: Intended Audience :: Developers
Classifier: License :: OSI Approved :: MIT License
Classifier: Operating System :: OS Independent
Classifier: Programming Language :: Python :: 3
Classifier: Programming Language :: Python :: 3 :: Only
Classifier: Topic :: Software Development :: Libraries
Classifier: Topic :: Utilities
Requires-Python: >=3
